stencil/__init__.py
stencil/timer.py
stencil/utils.py
stencil_data_science-0.2.dist-info/LICENSE
stencil_data_science-0.2.dist-info/METADATA
stencil_data_science-0.2.dist-info/WHEEL
stencil_data_science-0.2.dist-info/top_level.txt
stencil_data_science-0.2.dist-info/RECORD
